{
    "model_name": "convnext_tiny",
    "profiling_result": [
        {
            "batch": 1,
            "sm": 30,
            "quota": 10,
            "latency": 217.24501609802246
        },
        {
            "batch": 1,
            "sm": 30,
            "quota": 20,
            "latency": 82.29324499766032
        },
        {
            "batch": 1,
            "sm": 30,
            "quota": 30,
            "latency": 46.20235284169515
        },
        {
            "batch": 1,
            "sm": 30,
            "quota": 40,
            "latency": 41.99068069458008
        },
        {
            "batch": 1,
            "sm": 30,
            "quota": 50,
            "latency": 25.575412114461262
        },
        {
            "batch": 1,
            "sm": 30,
            "quota": 60,
            "latency": 26.499379475911457
        },
        {
            "batch": 1,
            "sm": 30,
            "quota": 70,
            "latency": 22.646236419677734
        },
        {
            "batch": 1,
            "sm": 30,
            "quota": 80,
            "latency": 17.728605270385742
        },
        {
            "batch": 1,
            "sm": 30,
            "quota": 90,
            "latency": 15.365017255147299
        },
        {
            "batch": 1,
            "sm": 30,
            "quota": 100,
            "latency": 14.198788007100424
        },
        {
            "batch": 2,
            "sm": 30,
            "quota": 10,
            "latency": 213.1623363494873
        },
        {
            "batch": 2,
            "sm": 30,
            "quota": 20,
            "latency": 83.43357563018799
        },
        {
            "batch": 2,
            "sm": 30,
            "quota": 30,
            "latency": 46.31344795227051
        },
        {
            "batch": 2,
            "sm": 30,
            "quota": 40,
            "latency": 41.7211389541626
        },
        {
            "batch": 2,
            "sm": 30,
            "quota": 50,
            "latency": 24.860417048136394
        },
        {
            "batch": 2,
            "sm": 30,
            "quota": 60,
            "latency": 26.4300537109375
        },
        {
            "batch": 2,
            "sm": 30,
            "quota": 70,
            "latency": 22.76625633239746
        },
        {
            "batch": 2,
            "sm": 30,
            "quota": 80,
            "latency": 17.688283920288086
        },
        {
            "batch": 2,
            "sm": 30,
            "quota": 90,
            "latency": 15.446993509928385
        },
        {
            "batch": 2,
            "sm": 30,
            "quota": 100,
            "latency": 15.31091054280599
        },
        {
            "batch": 4,
            "sm": 30,
            "quota": 10,
            "latency": 218.5137128829956
        },
        {
            "batch": 4,
            "sm": 30,
            "quota": 20,
            "latency": 82.70884831746419
        },
        {
            "batch": 4,
            "sm": 30,
            "quota": 30,
            "latency": 48.42631181081136
        },
        {
            "batch": 4,
            "sm": 30,
            "quota": 40,
            "latency": 42.000274658203125
        },
        {
            "batch": 4,
            "sm": 30,
            "quota": 50,
            "latency": 29.021423657735188
        },
        {
            "batch": 4,
            "sm": 30,
            "quota": 60,
            "latency": 26.502025922139484
        },
        {
            "batch": 4,
            "sm": 30,
            "quota": 70,
            "latency": 21.063717206319172
        },
        {
            "batch": 4,
            "sm": 30,
            "quota": 80,
            "latency": 16.218600273132324
        },
        {
            "batch": 4,
            "sm": 30,
            "quota": 90,
            "latency": 15.466618537902832
        },
        {
            "batch": 4,
            "sm": 30,
            "quota": 100,
            "latency": 15.50619920094808
        },
        {
            "batch": 8,
            "sm": 30,
            "quota": 10,
            "latency": 216.2592569986979
        },
        {
            "batch": 8,
            "sm": 30,
            "quota": 20,
            "latency": 84.58139260609944
        },
        {
            "batch": 8,
            "sm": 30,
            "quota": 30,
            "latency": 45.963683128356934
        },
        {
            "batch": 8,
            "sm": 30,
            "quota": 40,
            "latency": 43.39033921559652
        },
        {
            "batch": 8,
            "sm": 30,
            "quota": 50,
            "latency": 28.097972869873047
        },
        {
            "batch": 8,
            "sm": 30,
            "quota": 60,
            "latency": 27.8307310740153
        },
        {
            "batch": 8,
            "sm": 30,
            "quota": 70,
            "latency": 28.089429537455242
        },
        {
            "batch": 8,
            "sm": 30,
            "quota": 80,
            "latency": 28.462748527526855
        },
        {
            "batch": 8,
            "sm": 30,
            "quota": 90,
            "latency": 27.76600996653239
        },
        {
            "batch": 8,
            "sm": 30,
            "quota": 100,
            "latency": 27.77517795562744
        }
    ]
}