{
    "model_name": "densenet161",
    "profiling_result": [
        {
            "batch": 1,
            "sm": 30,
            "quota": 10,
            "latency": 882.9351878166199
        },
        {
            "batch": 1,
            "sm": 30,
            "quota": 20,
            "latency": 297.34861612319946
        },
        {
            "batch": 1,
            "sm": 30,
            "quota": 30,
            "latency": 186.2850785255432
        },
        {
            "batch": 1,
            "sm": 30,
            "quota": 40,
            "latency": 142.11466789245605
        },
        {
            "batch": 1,
            "sm": 30,
            "quota": 50,
            "latency": 103.0153751373291
        },
        {
            "batch": 1,
            "sm": 30,
            "quota": 60,
            "latency": 81.97062015533447
        },
        {
            "batch": 1,
            "sm": 30,
            "quota": 70,
            "latency": 67.11623191833496
        },
        {
            "batch": 1,
            "sm": 30,
            "quota": 80,
            "latency": 57.63596773147583
        },
        {
            "batch": 1,
            "sm": 30,
            "quota": 90,
            "latency": 51.79323196411133
        },
        {
            "batch": 1,
            "sm": 30,
            "quota": 100,
            "latency": 48.428544998168945
        },
        {
            "batch": 2,
            "sm": 30,
            "quota": 10,
            "latency": 905.4913210868835
        },
        {
            "batch": 2,
            "sm": 30,
            "quota": 20,
            "latency": 307.78844356536865
        },
        {
            "batch": 2,
            "sm": 30,
            "quota": 30,
            "latency": 189.80683088302612
        },
        {
            "batch": 2,
            "sm": 30,
            "quota": 40,
            "latency": 143.2306981086731
        },
        {
            "batch": 2,
            "sm": 30,
            "quota": 50,
            "latency": 106.58253908157349
        },
        {
            "batch": 2,
            "sm": 30,
            "quota": 60,
            "latency": 85.094473361969
        },
        {
            "batch": 2,
            "sm": 30,
            "quota": 70,
            "latency": 67.84457445144653
        },
        {
            "batch": 2,
            "sm": 30,
            "quota": 80,
            "latency": 58.012123107910156
        },
        {
            "batch": 2,
            "sm": 30,
            "quota": 90,
            "latency": 51.88887596130371
        },
        {
            "batch": 2,
            "sm": 30,
            "quota": 100,
            "latency": 49.09324407577515
        },
        {
            "batch": 4,
            "sm": 30,
            "quota": 10,
            "latency": 887.5828051567078
        },
        {
            "batch": 4,
            "sm": 30,
            "quota": 20,
            "latency": 308.8994526863098
        },
        {
            "batch": 4,
            "sm": 30,
            "quota": 30,
            "latency": 191.19865655899048
        },
        {
            "batch": 4,
            "sm": 30,
            "quota": 40,
            "latency": 144.02892589569092
        },
        {
            "batch": 4,
            "sm": 30,
            "quota": 50,
            "latency": 107.34272956848145
        },
        {
            "batch": 4,
            "sm": 30,
            "quota": 60,
            "latency": 84.41797494888306
        },
        {
            "batch": 4,
            "sm": 30,
            "quota": 70,
            "latency": 67.39421129226685
        },
        {
            "batch": 4,
            "sm": 30,
            "quota": 80,
            "latency": 57.82942295074463
        },
        {
            "batch": 4,
            "sm": 30,
            "quota": 90,
            "latency": 52.08861827850342
        },
        {
            "batch": 4,
            "sm": 30,
            "quota": 100,
            "latency": 50.01734733581543
        },
        {
            "batch": 8,
            "sm": 30,
            "quota": 10,
            "latency": 873.3514451980591
        },
        {
            "batch": 8,
            "sm": 30,
            "quota": 20,
            "latency": 296.7998218536377
        },
        {
            "batch": 8,
            "sm": 30,
            "quota": 30,
            "latency": 187.5632357597351
        },
        {
            "batch": 8,
            "sm": 30,
            "quota": 40,
            "latency": 141.58954858779907
        },
        {
            "batch": 8,
            "sm": 30,
            "quota": 50,
            "latency": 103.99754524230957
        },
        {
            "batch": 8,
            "sm": 30,
            "quota": 60,
            "latency": 81.03853702545166
        },
        {
            "batch": 8,
            "sm": 30,
            "quota": 70,
            "latency": 67.65327453613281
        },
        {
            "batch": 8,
            "sm": 30,
            "quota": 80,
            "latency": 61.4272665977478
        },
        {
            "batch": 8,
            "sm": 30,
            "quota": 90,
            "latency": 57.771124839782715
        },
        {
            "batch": 8,
            "sm": 30,
            "quota": 100,
            "latency": 61.432671546936035
        }
    ]
}