{
    "model_name": "densenet201",
    "profiling_result": [
        {
            "batch": 1,
            "sm": 100,
            "quota": 10,
            "latency": 1121.6534352302551
        },
        {
            "batch": 1,
            "sm": 100,
            "quota": 20,
            "latency": 381.96197271347046
        },
        {
            "batch": 1,
            "sm": 100,
            "quota": 30,
            "latency": 240.83429098129272
        },
        {
            "batch": 1,
            "sm": 100,
            "quota": 40,
            "latency": 180.88402271270752
        },
        {
            "batch": 1,
            "sm": 100,
            "quota": 50,
            "latency": 140.92463970184326
        },
        {
            "batch": 1,
            "sm": 100,
            "quota": 60,
            "latency": 104.68652248382568
        },
        {
            "batch": 1,
            "sm": 100,
            "quota": 70,
            "latency": 89.99152183532715
        },
        {
            "batch": 1,
            "sm": 100,
            "quota": 80,
            "latency": 65.92031240463257
        },
        {
            "batch": 1,
            "sm": 100,
            "quota": 90,
            "latency": 61.39326095581055
        },
        {
            "batch": 1,
            "sm": 100,
            "quota": 100,
            "latency": 56.593971252441406
        },
        {
            "batch": 2,
            "sm": 100,
            "quota": 10,
            "latency": 1095.3377723693848
        },
        {
            "batch": 2,
            "sm": 100,
            "quota": 20,
            "latency": 384.46279525756836
        },
        {
            "batch": 2,
            "sm": 100,
            "quota": 30,
            "latency": 236.4105749130249
        },
        {
            "batch": 2,
            "sm": 100,
            "quota": 40,
            "latency": 182.08873987197876
        },
        {
            "batch": 2,
            "sm": 100,
            "quota": 50,
            "latency": 134.45674657821655
        },
        {
            "batch": 2,
            "sm": 100,
            "quota": 60,
            "latency": 102.63883590698242
        },
        {
            "batch": 2,
            "sm": 100,
            "quota": 70,
            "latency": 82.7516222000122
        },
        {
            "batch": 2,
            "sm": 100,
            "quota": 80,
            "latency": 65.96341371536255
        },
        {
            "batch": 2,
            "sm": 100,
            "quota": 90,
            "latency": 59.88016128540039
        },
        {
            "batch": 2,
            "sm": 100,
            "quota": 100,
            "latency": 57.79014348983765
        },
        {
            "batch": 4,
            "sm": 100,
            "quota": 10,
            "latency": 1116.2106680870056
        },
        {
            "batch": 4,
            "sm": 100,
            "quota": 20,
            "latency": 375.54943799972534
        },
        {
            "batch": 4,
            "sm": 100,
            "quota": 30,
            "latency": 237.6354718208313
        },
        {
            "batch": 4,
            "sm": 100,
            "quota": 40,
            "latency": 178.57386350631714
        },
        {
            "batch": 4,
            "sm": 100,
            "quota": 50,
            "latency": 131.19858264923096
        },
        {
            "batch": 4,
            "sm": 100,
            "quota": 60,
            "latency": 102.99761056900024
        },
        {
            "batch": 4,
            "sm": 100,
            "quota": 70,
            "latency": 82.55903720855713
        },
        {
            "batch": 4,
            "sm": 100,
            "quota": 80,
            "latency": 66.38854265213013
        },
        {
            "batch": 4,
            "sm": 100,
            "quota": 90,
            "latency": 60.440733432769775
        },
        {
            "batch": 4,
            "sm": 100,
            "quota": 100,
            "latency": 61.27718210220337
        },
        {
            "batch": 8,
            "sm": 100,
            "quota": 10,
            "latency": 1123.806746006012
        },
        {
            "batch": 8,
            "sm": 100,
            "quota": 20,
            "latency": 382.092547416687
        },
        {
            "batch": 8,
            "sm": 100,
            "quota": 30,
            "latency": 240.6962251663208
        },
        {
            "batch": 8,
            "sm": 100,
            "quota": 40,
            "latency": 180.18897771835327
        },
        {
            "batch": 8,
            "sm": 100,
            "quota": 50,
            "latency": 135.48001050949097
        },
        {
            "batch": 8,
            "sm": 100,
            "quota": 60,
            "latency": 101.82328224182129
        },
        {
            "batch": 8,
            "sm": 100,
            "quota": 70,
            "latency": 85.05895614624023
        },
        {
            "batch": 8,
            "sm": 100,
            "quota": 80,
            "latency": 66.55832529067993
        },
        {
            "batch": 8,
            "sm": 100,
            "quota": 90,
            "latency": 61.50534629821777
        },
        {
            "batch": 8,
            "sm": 100,
            "quota": 100,
            "latency": 57.455198764801025
        }
    ]
}