{
    "model_name": "densenet161",
    "profiling_result": [
        {
            "batch": 1,
            "sm": 25,
            "quota": 10,
            "latency": 882.6781463623047
        },
        {
            "batch": 1,
            "sm": 25,
            "quota": 20,
            "latency": 291.22790575027466
        },
        {
            "batch": 1,
            "sm": 25,
            "quota": 30,
            "latency": 184.11515474319458
        },
        {
            "batch": 1,
            "sm": 25,
            "quota": 40,
            "latency": 137.47207641601562
        },
        {
            "batch": 1,
            "sm": 25,
            "quota": 50,
            "latency": 106.18147134780884
        },
        {
            "batch": 1,
            "sm": 25,
            "quota": 60,
            "latency": 81.628737449646
        },
        {
            "batch": 1,
            "sm": 25,
            "quota": 70,
            "latency": 67.01295375823975
        },
        {
            "batch": 1,
            "sm": 25,
            "quota": 80,
            "latency": 57.45023488998413
        },
        {
            "batch": 1,
            "sm": 25,
            "quota": 90,
            "latency": 51.186323165893555
        },
        {
            "batch": 1,
            "sm": 25,
            "quota": 100,
            "latency": 51.26107454299927
        },
        {
            "batch": 2,
            "sm": 25,
            "quota": 10,
            "latency": 888.2840085029602
        },
        {
            "batch": 2,
            "sm": 25,
            "quota": 20,
            "latency": 300.04889965057373
        },
        {
            "batch": 2,
            "sm": 25,
            "quota": 30,
            "latency": 198.86343240737915
        },
        {
            "batch": 2,
            "sm": 25,
            "quota": 40,
            "latency": 145.80118894577026
        },
        {
            "batch": 2,
            "sm": 25,
            "quota": 50,
            "latency": 105.7967758178711
        },
        {
            "batch": 2,
            "sm": 25,
            "quota": 60,
            "latency": 83.72323989868164
        },
        {
            "batch": 2,
            "sm": 25,
            "quota": 70,
            "latency": 68.26437711715698
        },
        {
            "batch": 2,
            "sm": 25,
            "quota": 80,
            "latency": 60.24022102355957
        },
        {
            "batch": 2,
            "sm": 25,
            "quota": 90,
            "latency": 52.13182210922241
        },
        {
            "batch": 2,
            "sm": 25,
            "quota": 100,
            "latency": 48.221893310546875
        },
        {
            "batch": 4,
            "sm": 25,
            "quota": 10,
            "latency": 905.915801525116
        },
        {
            "batch": 4,
            "sm": 25,
            "quota": 20,
            "latency": 296.47868633270264
        },
        {
            "batch": 4,
            "sm": 25,
            "quota": 30,
            "latency": 190.395770072937
        },
        {
            "batch": 4,
            "sm": 25,
            "quota": 40,
            "latency": 144.56583261489868
        },
        {
            "batch": 4,
            "sm": 25,
            "quota": 50,
            "latency": 109.98772144317627
        },
        {
            "batch": 4,
            "sm": 25,
            "quota": 60,
            "latency": 87.36561059951782
        },
        {
            "batch": 4,
            "sm": 25,
            "quota": 70,
            "latency": 68.67278575897217
        },
        {
            "batch": 4,
            "sm": 25,
            "quota": 80,
            "latency": 57.40954399108887
        },
        {
            "batch": 4,
            "sm": 25,
            "quota": 90,
            "latency": 53.097336292266846
        },
        {
            "batch": 4,
            "sm": 25,
            "quota": 100,
            "latency": 48.93197536468506
        },
        {
            "batch": 8,
            "sm": 25,
            "quota": 10,
            "latency": 869.7335743904114
        },
        {
            "batch": 8,
            "sm": 25,
            "quota": 20,
            "latency": 301.14484548568726
        },
        {
            "batch": 8,
            "sm": 25,
            "quota": 30,
            "latency": 186.9800305366516
        },
        {
            "batch": 8,
            "sm": 25,
            "quota": 40,
            "latency": 141.12125635147095
        },
        {
            "batch": 8,
            "sm": 25,
            "quota": 50,
            "latency": 102.3009181022644
        },
        {
            "batch": 8,
            "sm": 25,
            "quota": 60,
            "latency": 81.43828868865967
        },
        {
            "batch": 8,
            "sm": 25,
            "quota": 70,
            "latency": 71.50324821472168
        },
        {
            "batch": 8,
            "sm": 25,
            "quota": 80,
            "latency": 67.82521724700928
        },
        {
            "batch": 8,
            "sm": 25,
            "quota": 90,
            "latency": 67.751145362854
        },
        {
            "batch": 8,
            "sm": 25,
            "quota": 100,
            "latency": 68.05220365524292
        }
    ]
}