{
    "model_name": "mnasnet0_5",
    "profiling_result": [
        {
            "batch": 1,
            "sm": 60,
            "quota": 10,
            "latency": 210.11796156565347
        },
        {
            "batch": 1,
            "sm": 60,
            "quota": 20,
            "latency": 76.24337037404378
        },
        {
            "batch": 1,
            "sm": 60,
            "quota": 30,
            "latency": 45.936876932779946
        },
        {
            "batch": 1,
            "sm": 60,
            "quota": 40,
            "latency": 41.90181573232015
        },
        {
            "batch": 1,
            "sm": 60,
            "quota": 50,
            "latency": 24.968751271565754
        },
        {
            "batch": 1,
            "sm": 60,
            "quota": 60,
            "latency": 26.082282066345215
        },
        {
            "batch": 1,
            "sm": 60,
            "quota": 70,
            "latency": 21.14914894104004
        },
        {
            "batch": 1,
            "sm": 60,
            "quota": 80,
            "latency": 16.262272198994953
        },
        {
            "batch": 1,
            "sm": 60,
            "quota": 90,
            "latency": 14.756147066752115
        },
        {
            "batch": 1,
            "sm": 60,
            "quota": 100,
            "latency": 13.596013387044271
        },
        {
            "batch": 2,
            "sm": 60,
            "quota": 10,
            "latency": 210.8599313100179
        },
        {
            "batch": 2,
            "sm": 60,
            "quota": 20,
            "latency": 72.0972188313802
        },
        {
            "batch": 2,
            "sm": 60,
            "quota": 30,
            "latency": 46.17377599080404
        },
        {
            "batch": 2,
            "sm": 60,
            "quota": 40,
            "latency": 41.61490122477213
        },
        {
            "batch": 2,
            "sm": 60,
            "quota": 50,
            "latency": 24.572415351867676
        },
        {
            "batch": 2,
            "sm": 60,
            "quota": 60,
            "latency": 26.057861646016438
        },
        {
            "batch": 2,
            "sm": 60,
            "quota": 70,
            "latency": 21.394600868225098
        },
        {
            "batch": 2,
            "sm": 60,
            "quota": 80,
            "latency": 17.10030396779378
        },
        {
            "batch": 2,
            "sm": 60,
            "quota": 90,
            "latency": 15.235390663146973
        },
        {
            "batch": 2,
            "sm": 60,
            "quota": 100,
            "latency": 13.716716766357422
        },
        {
            "batch": 4,
            "sm": 60,
            "quota": 10,
            "latency": 214.8335806528727
        },
        {
            "batch": 4,
            "sm": 60,
            "quota": 20,
            "latency": 80.85273901621501
        },
        {
            "batch": 4,
            "sm": 60,
            "quota": 30,
            "latency": 46.28687063852946
        },
        {
            "batch": 4,
            "sm": 60,
            "quota": 40,
            "latency": 41.853338877360024
        },
        {
            "batch": 4,
            "sm": 60,
            "quota": 50,
            "latency": 24.980106353759766
        },
        {
            "batch": 4,
            "sm": 60,
            "quota": 60,
            "latency": 25.051684379577637
        },
        {
            "batch": 4,
            "sm": 60,
            "quota": 70,
            "latency": 20.997002919514973
        },
        {
            "batch": 4,
            "sm": 60,
            "quota": 80,
            "latency": 17.70506223042806
        },
        {
            "batch": 4,
            "sm": 60,
            "quota": 90,
            "latency": 14.90676244099935
        },
        {
            "batch": 4,
            "sm": 60,
            "quota": 100,
            "latency": 13.304378191630045
        },
        {
            "batch": 8,
            "sm": 60,
            "quota": 10,
            "latency": 214.4547700881958
        },
        {
            "batch": 8,
            "sm": 60,
            "quota": 20,
            "latency": 81.44979794820149
        },
        {
            "batch": 8,
            "sm": 60,
            "quota": 30,
            "latency": 46.59949938456217
        },
        {
            "batch": 8,
            "sm": 60,
            "quota": 40,
            "latency": 41.87181790669759
        },
        {
            "batch": 8,
            "sm": 60,
            "quota": 50,
            "latency": 25.420918464660645
        },
        {
            "batch": 8,
            "sm": 60,
            "quota": 60,
            "latency": 25.998183886210125
        },
        {
            "batch": 8,
            "sm": 60,
            "quota": 70,
            "latency": 21.882370313008625
        },
        {
            "batch": 8,
            "sm": 60,
            "quota": 80,
            "latency": 16.94109280904134
        },
        {
            "batch": 8,
            "sm": 60,
            "quota": 90,
            "latency": 14.754571914672852
        },
        {
            "batch": 8,
            "sm": 60,
            "quota": 100,
            "latency": 13.657879829406738
        }
    ]
}