{
    "model_name": "mnasnet0_5",
    "profiling_result": [
        {
            "batch": 1,
            "sm": 20,
            "quota": 10,
            "latency": 206.24706109364828
        },
        {
            "batch": 1,
            "sm": 20,
            "quota": 20,
            "latency": 66.9644037882487
        },
        {
            "batch": 1,
            "sm": 20,
            "quota": 30,
            "latency": 45.91212113698324
        },
        {
            "batch": 1,
            "sm": 20,
            "quota": 40,
            "latency": 41.33324782053629
        },
        {
            "batch": 1,
            "sm": 20,
            "quota": 50,
            "latency": 24.58399772644043
        },
        {
            "batch": 1,
            "sm": 20,
            "quota": 60,
            "latency": 25.85259437561035
        },
        {
            "batch": 1,
            "sm": 20,
            "quota": 70,
            "latency": 21.23897393544515
        },
        {
            "batch": 1,
            "sm": 20,
            "quota": 80,
            "latency": 16.291414896647137
        },
        {
            "batch": 1,
            "sm": 20,
            "quota": 90,
            "latency": 14.496057828267416
        },
        {
            "batch": 1,
            "sm": 20,
            "quota": 100,
            "latency": 14.411390622456869
        },
        {
            "batch": 2,
            "sm": 20,
            "quota": 10,
            "latency": 205.83277066548666
        },
        {
            "batch": 2,
            "sm": 20,
            "quota": 20,
            "latency": 83.92200628916423
        },
        {
            "batch": 2,
            "sm": 20,
            "quota": 30,
            "latency": 45.67234516143799
        },
        {
            "batch": 2,
            "sm": 20,
            "quota": 40,
            "latency": 40.55097897847494
        },
        {
            "batch": 2,
            "sm": 20,
            "quota": 50,
            "latency": 24.61525281270345
        },
        {
            "batch": 2,
            "sm": 20,
            "quota": 60,
            "latency": 25.820587476094563
        },
        {
            "batch": 2,
            "sm": 20,
            "quota": 70,
            "latency": 20.790212949117024
        },
        {
            "batch": 2,
            "sm": 20,
            "quota": 80,
            "latency": 15.53825855255127
        },
        {
            "batch": 2,
            "sm": 20,
            "quota": 90,
            "latency": 14.955023129781088
        },
        {
            "batch": 2,
            "sm": 20,
            "quota": 100,
            "latency": 13.33203156789144
        },
        {
            "batch": 4,
            "sm": 20,
            "quota": 10,
            "latency": 212.40864594777426
        },
        {
            "batch": 4,
            "sm": 20,
            "quota": 20,
            "latency": 74.96433893839519
        },
        {
            "batch": 4,
            "sm": 20,
            "quota": 30,
            "latency": 48.41752370198568
        },
        {
            "batch": 4,
            "sm": 20,
            "quota": 40,
            "latency": 40.10894775390625
        },
        {
            "batch": 4,
            "sm": 20,
            "quota": 50,
            "latency": 25.005284945170086
        },
        {
            "batch": 4,
            "sm": 20,
            "quota": 60,
            "latency": 26.011109352111816
        },
        {
            "batch": 4,
            "sm": 20,
            "quota": 70,
            "latency": 21.878918011983234
        },
        {
            "batch": 4,
            "sm": 20,
            "quota": 80,
            "latency": 18.081908226013184
        },
        {
            "batch": 4,
            "sm": 20,
            "quota": 90,
            "latency": 16.143059730529785
        },
        {
            "batch": 4,
            "sm": 20,
            "quota": 100,
            "latency": 14.120095570882162
        },
        {
            "batch": 8,
            "sm": 20,
            "quota": 10,
            "latency": 211.79173787434897
        },
        {
            "batch": 8,
            "sm": 20,
            "quota": 20,
            "latency": 78.24099063873291
        },
        {
            "batch": 8,
            "sm": 20,
            "quota": 30,
            "latency": 45.95097064971924
        },
        {
            "batch": 8,
            "sm": 20,
            "quota": 40,
            "latency": 41.76627159118652
        },
        {
            "batch": 8,
            "sm": 20,
            "quota": 50,
            "latency": 24.83910083770752
        },
        {
            "batch": 8,
            "sm": 20,
            "quota": 60,
            "latency": 26.365397771199543
        },
        {
            "batch": 8,
            "sm": 20,
            "quota": 70,
            "latency": 21.245349248250324
        },
        {
            "batch": 8,
            "sm": 20,
            "quota": 80,
            "latency": 17.005031903584797
        },
        {
            "batch": 8,
            "sm": 20,
            "quota": 90,
            "latency": 15.207804044087728
        },
        {
            "batch": 8,
            "sm": 20,
            "quota": 100,
            "latency": 13.97641658782959
        }
    ]
}