{
    "model_name": "resnext101_64x4d",
    "profiling_result": [
        {
            "batch": 1,
            "sm": 5,
            "quota": 10,
            "latency": 474.089840054512
        },
        {
            "batch": 1,
            "sm": 5,
            "quota": 20,
            "latency": 160.64473688602448
        },
        {
            "batch": 1,
            "sm": 5,
            "quota": 30,
            "latency": 108.1449568271637
        },
        {
            "batch": 1,
            "sm": 5,
            "quota": 40,
            "latency": 106.22114539146423
        },
        {
            "batch": 1,
            "sm": 5,
            "quota": 50,
            "latency": 106.21224045753479
        },
        {
            "batch": 1,
            "sm": 5,
            "quota": 60,
            "latency": 105.87791800498962
        },
        {
            "batch": 1,
            "sm": 5,
            "quota": 70,
            "latency": 105.87326288223267
        },
        {
            "batch": 1,
            "sm": 5,
            "quota": 80,
            "latency": 106.46545588970184
        },
        {
            "batch": 1,
            "sm": 5,
            "quota": 90,
            "latency": 106.38996660709381
        },
        {
            "batch": 1,
            "sm": 5,
            "quota": 100,
            "latency": 106.09994232654572
        },
        {
            "batch": 2,
            "sm": 5,
            "quota": 10,
            "latency": 526.5290588140488
        },
        {
            "batch": 2,
            "sm": 5,
            "quota": 20,
            "latency": 211.96599900722504
        },
        {
            "batch": 2,
            "sm": 5,
            "quota": 30,
            "latency": 210.4908436536789
        },
        {
            "batch": 2,
            "sm": 5,
            "quota": 40,
            "latency": 210.06942689418793
        },
        {
            "batch": 2,
            "sm": 5,
            "quota": 50,
            "latency": 210.28200387954712
        },
        {
            "batch": 2,
            "sm": 5,
            "quota": 60,
            "latency": 210.19709706306458
        },
        {
            "batch": 2,
            "sm": 5,
            "quota": 70,
            "latency": 210.33064424991608
        },
        {
            "batch": 2,
            "sm": 5,
            "quota": 80,
            "latency": 209.8899781703949
        },
        {
            "batch": 2,
            "sm": 5,
            "quota": 90,
            "latency": 209.8974883556366
        },
        {
            "batch": 2,
            "sm": 5,
            "quota": 100,
            "latency": 210.19188463687897
        },
        {
            "batch": 4,
            "sm": 5,
            "quota": 10,
            "latency": 743.8757300376892
        },
        {
            "batch": 4,
            "sm": 5,
            "quota": 20,
            "latency": 273.8189399242401
        },
        {
            "batch": 4,
            "sm": 5,
            "quota": 30,
            "latency": 273.2579290866852
        },
        {
            "batch": 4,
            "sm": 5,
            "quota": 40,
            "latency": 273.21595549583435
        },
        {
            "batch": 4,
            "sm": 5,
            "quota": 50,
            "latency": 273.4307825565338
        },
        {
            "batch": 4,
            "sm": 5,
            "quota": 60,
            "latency": 273.1080502271652
        },
        {
            "batch": 4,
            "sm": 5,
            "quota": 70,
            "latency": 272.66944646835327
        },
        {
            "batch": 4,
            "sm": 5,
            "quota": 80,
            "latency": 273.513600230217
        },
        {
            "batch": 4,
            "sm": 5,
            "quota": 90,
            "latency": 272.7323830127716
        },
        {
            "batch": 4,
            "sm": 5,
            "quota": 100,
            "latency": 272.1735417842865
        },
        {
            "batch": 8,
            "sm": 5,
            "quota": 10,
            "latency": 751.6083300113678
        },
        {
            "batch": 8,
            "sm": 5,
            "quota": 20,
            "latency": 517.3204928636551
        },
        {
            "batch": 8,
            "sm": 5,
            "quota": 30,
            "latency": 516.9655948877335
        },
        {
            "batch": 8,
            "sm": 5,
            "quota": 40,
            "latency": 517.6078677177429
        },
        {
            "batch": 8,
            "sm": 5,
            "quota": 50,
            "latency": 517.1248227357864
        },
        {
            "batch": 8,
            "sm": 5,
            "quota": 60,
            "latency": 516.7235195636749
        },
        {
            "batch": 8,
            "sm": 5,
            "quota": 70,
            "latency": 516.1288321018219
        },
        {
            "batch": 8,
            "sm": 5,
            "quota": 80,
            "latency": 517.2425270080566
        },
        {
            "batch": 8,
            "sm": 5,
            "quota": 90,
            "latency": 516.566264629364
        },
        {
            "batch": 8,
            "sm": 5,
            "quota": 100,
            "latency": 516.4681732654572
        }
    ]
}