{
    "model_name": "vgg19_bn",
    "profiling_result": [
        {
            "batch": 1,
            "sm": 30,
            "quota": 10,
            "latency": 88.96336555480957
        },
        {
            "batch": 1,
            "sm": 30,
            "quota": 20,
            "latency": 26.882736682891846
        },
        {
            "batch": 1,
            "sm": 30,
            "quota": 30,
            "latency": 11.634535789489746
        },
        {
            "batch": 1,
            "sm": 30,
            "quota": 40,
            "latency": 10.830016136169434
        },
        {
            "batch": 1,
            "sm": 30,
            "quota": 50,
            "latency": 11.138150691986084
        },
        {
            "batch": 1,
            "sm": 30,
            "quota": 60,
            "latency": 10.53983211517334
        },
        {
            "batch": 1,
            "sm": 30,
            "quota": 70,
            "latency": 11.023011207580566
        },
        {
            "batch": 1,
            "sm": 30,
            "quota": 80,
            "latency": 10.449795722961426
        },
        {
            "batch": 1,
            "sm": 30,
            "quota": 90,
            "latency": 10.749337673187256
        },
        {
            "batch": 1,
            "sm": 30,
            "quota": 100,
            "latency": 10.29742956161499
        },
        {
            "batch": 2,
            "sm": 30,
            "quota": 10,
            "latency": 90.15613794326782
        },
        {
            "batch": 2,
            "sm": 30,
            "quota": 20,
            "latency": 26.74100399017334
        },
        {
            "batch": 2,
            "sm": 30,
            "quota": 30,
            "latency": 18.083386421203613
        },
        {
            "batch": 2,
            "sm": 30,
            "quota": 40,
            "latency": 16.443614959716797
        },
        {
            "batch": 2,
            "sm": 30,
            "quota": 50,
            "latency": 17.440474033355713
        },
        {
            "batch": 2,
            "sm": 30,
            "quota": 60,
            "latency": 16.515116691589355
        },
        {
            "batch": 2,
            "sm": 30,
            "quota": 70,
            "latency": 17.26818084716797
        },
        {
            "batch": 2,
            "sm": 30,
            "quota": 80,
            "latency": 16.55010461807251
        },
        {
            "batch": 2,
            "sm": 30,
            "quota": 90,
            "latency": 17.1926212310791
        },
        {
            "batch": 2,
            "sm": 30,
            "quota": 100,
            "latency": 16.60759925842285
        },
        {
            "batch": 4,
            "sm": 30,
            "quota": 10,
            "latency": 92.58317470550537
        },
        {
            "batch": 4,
            "sm": 30,
            "quota": 20,
            "latency": 30.46926259994507
        },
        {
            "batch": 4,
            "sm": 30,
            "quota": 30,
            "latency": 32.059335708618164
        },
        {
            "batch": 4,
            "sm": 30,
            "quota": 40,
            "latency": 30.002388954162598
        },
        {
            "batch": 4,
            "sm": 30,
            "quota": 50,
            "latency": 32.284560203552246
        },
        {
            "batch": 4,
            "sm": 30,
            "quota": 60,
            "latency": 30.08537769317627
        },
        {
            "batch": 4,
            "sm": 30,
            "quota": 70,
            "latency": 32.75047302246094
        },
        {
            "batch": 4,
            "sm": 30,
            "quota": 80,
            "latency": 30.096445083618164
        },
        {
            "batch": 4,
            "sm": 30,
            "quota": 90,
            "latency": 32.75780439376831
        },
        {
            "batch": 4,
            "sm": 30,
            "quota": 100,
            "latency": 30.113978385925293
        },
        {
            "batch": 8,
            "sm": 30,
            "quota": 10,
            "latency": 90.24089574813843
        },
        {
            "batch": 8,
            "sm": 30,
            "quota": 20,
            "latency": 58.45713138580322
        },
        {
            "batch": 8,
            "sm": 30,
            "quota": 30,
            "latency": 56.556031703948975
        },
        {
            "batch": 8,
            "sm": 30,
            "quota": 40,
            "latency": 60.01424789428711
        },
        {
            "batch": 8,
            "sm": 30,
            "quota": 50,
            "latency": 56.445472240448
        },
        {
            "batch": 8,
            "sm": 30,
            "quota": 60,
            "latency": 61.93148612976074
        },
        {
            "batch": 8,
            "sm": 30,
            "quota": 70,
            "latency": 57.4999213218689
        },
        {
            "batch": 8,
            "sm": 30,
            "quota": 80,
            "latency": 56.47920846939087
        },
        {
            "batch": 8,
            "sm": 30,
            "quota": 90,
            "latency": 59.35379505157471
        },
        {
            "batch": 8,
            "sm": 30,
            "quota": 100,
            "latency": 56.397483348846436
        }
    ]
}